vector_inspector-0.3.11.dist-info/METADATA
vector_inspector-0.3.11.dist-info/WHEEL
vector_inspector-0.3.11.dist-info/entry_points.txt
vector_inspector/__init__.py
vector_inspector/__main__.py
vector_inspector/config/__init__.py
vector_inspector/config/known_embedding_models.json
vector_inspector/core/__init__.py
vector_inspector/core/cache_manager.py
vector_inspector/core/connection_manager.py
vector_inspector/core/connections/__init__.py
vector_inspector/core/connections/base_connection.py
vector_inspector/core/connections/chroma_connection.py
vector_inspector/core/connections/pgvector_connection.py
vector_inspector/core/connections/pinecone_connection.py
vector_inspector/core/connections/qdrant_connection.py
vector_inspector/core/connections/qdrant_helpers/__init__.py
vector_inspector/core/connections/qdrant_helpers/qdrant_embedding_resolver.py
vector_inspector/core/connections/qdrant_helpers/qdrant_filter_builder.py
vector_inspector/core/connections/template_connection.py
vector_inspector/core/embedding_providers/__init__.py
vector_inspector/core/embedding_providers/base_provider.py
vector_inspector/core/embedding_providers/clip_provider.py
vector_inspector/core/embedding_providers/provider_factory.py
vector_inspector/core/embedding_providers/sentence_transformer_provider.py
vector_inspector/core/embedding_utils.py
vector_inspector/core/logging.py
vector_inspector/core/model_registry.py
vector_inspector/core/provider_factory.py
vector_inspector/extensions/__init__.py
vector_inspector/extensions/telemetry_settings_panel.py
vector_inspector/main.py
vector_inspector/services/__init__.py
vector_inspector/services/backup_helpers.py
vector_inspector/services/backup_restore_service.py
vector_inspector/services/credential_service.py
vector_inspector/services/filter_service.py
vector_inspector/services/import_export_service.py
vector_inspector/services/profile_service.py
vector_inspector/services/settings_service.py
vector_inspector/services/telemetry_service.py
vector_inspector/services/update_service.py
vector_inspector/services/visualization_service.py
vector_inspector/ui/__init__.py
vector_inspector-0.3.11.dist-info/RECORD
