Metadata-Version: 2.1
Name: vector-inspector
Version: 0.3.11
Summary: A comprehensive desktop application for visualizing, querying, and managing vector database data
Author-Email: Anthony Dawson <anthonypdawson+github@gmail.com>
License: MIT
Project-URL: Homepage, https://vector-inspector.divinedevops.com
Project-URL: Source, https://github.com/anthonypdawson/vector-inspector
Project-URL: Issues, https://github.com/anthonypdawson/vector-inspector/issues
Project-URL: Documentation, https://github.com/anthonypdawson/vector-inspector#readme
Requires-Python: >=3.10
Requires-Dist: chromadb>=0.4.22
Requires-Dist: qdrant-client>=1.7.0
Requires-Dist: pyside6>=6.6.0
Requires-Dist: PySide6-Addons>=6.6.3.1
Requires-Dist: pandas>=2.1.0
Requires-Dist: numpy>=1.26.0
Requires-Dist: scikit-learn>=1.3.0
Requires-Dist: umap-learn>=0.5.5
Requires-Dist: plotly>=5.18.0
Requires-Dist: sentence-transformers>=2.2.0
Requires-Dist: fastembed>=0.7.4
Requires-Dist: pyarrow>=14.0.0
Requires-Dist: pinecone>=8.0.0
Requires-Dist: keyring>=25.7.0
Requires-Dist: hf-xet>=1.2.0
Requires-Dist: pymilvus>=2.6.6
Requires-Dist: lancedb>=0.27.0
Requires-Dist: psycopg2>=2.9.11
Requires-Dist: pgvector>=0.4.2
